vo/__init__.py
vo/value.py
vo-0.3.0.dist-info/DESCRIPTION.rst
vo-0.3.0.dist-info/METADATA
vo-0.3.0.dist-info/RECORD
vo-0.3.0.dist-info/WHEEL
vo-0.3.0.dist-info/metadata.json
vo-0.3.0.dist-info/top_level.txt
