Metadata-Version: 2.0
Name: vo
Version: 0.3.0
Summary: DDD Value Objects implementation
Home-page: https://github.com/pawelzny/vo
Author: Paweł Zadrożny @pawelzny
Author-email: pawel.zny@gmail.com
License: ISC (ISCL)
Keywords: value data object DDD
Platform: UNKNOWN
Classifier: Development Status :: 4 - Beta
Classifier: Intended Audience :: Developers
Classifier: Natural Language :: English
Classifier: Programming Language :: Python :: 3.4
Classifier: Programming Language :: Python :: 3.5
Classifier: Programming Language :: Python :: 3.6
Classifier: Programming Language :: Python :: 3 :: Only
Classifier: License :: OSI Approved :: ISC License (ISCL)
Classifier: Topic :: Software Development
Classifier: Topic :: Software Development :: Libraries :: Python Modules
Requires-Dist: setuptools-scm
